AUTHORS.rst
CONTRIBUTING.rst
HISTORY.rst
LICENSE
MANIFEST.in
README.rst
requirements.txt
requirements_dev.txt
setup.cfg
setup.py
docs/Makefile
docs/authors.rst
docs/conf.py
docs/contributing.rst
docs/history.rst
docs/index.rst
docs/installation.rst
docs/make.bat
docs/readme.rst
docs/usage.rst
serialization/__init__.py
serialization/adapter.py
serialization/adapters.py
serialization/annotate.py
serialization/base.py
serialization/formatable.py
serialization/interface.py
serialization/json_.py
serialization/pytree.py
serialization/reflect.py
serialization/registry.py
serialization/sexp.py
serialization.egg-info/PKG-INFO
serialization.egg-info/SOURCES.txt
serialization.egg-info/dependency_links.txt
serialization.egg-info/not-zip-safe
serialization.egg-info/requires.txt
serialization.egg-info/top_level.txt
tests/__init__.py
tests/conftest.py
tests/test_adapters.py
tests/test_annotate.py
tests/test_base.py
tests/test_formatable.py
tests/test_json.py
tests/test_pytree.py
tests/test_reflect.py
tests/test_sexp.py
tests/utils.py