Metadata-Version: 2.1
Name: serialization
Version: 1.2.3
Summary: Smart serialization library for Python language
Home-page: https://github.com/rumblefishdev/serialization
Author: Sebastien Merle, Marek Kowalski, Mateusz Probachta
Author-email: s.merle@gmail.com, kowalski0123@gmail.com, mateusz.probachta@pragmaticcoders.com
License: GPL
Keywords: serialization
Platform: UNKNOWN
Classifier: Development Status :: 2 - Pre-Alpha
Classifier: Intended Audience :: Developers
Classifier: License :: OSI Approved :: GNU General Public License (GPL)
Classifier: Natural Language :: English
Classifier: Programming Language :: Python :: 2
Classifier: Programming Language :: Python :: 2.7
Classifier: Programming Language :: Python :: 3
Classifier: Programming Language :: Python :: 3.3
Classifier: Programming Language :: Python :: 3.4
Classifier: Programming Language :: Python :: 3.5
Classifier: Programming Language :: Python :: 3.6
Classifier: Programming Language :: Python :: 3.7
Classifier: Programming Language :: Python :: 3.8
Provides-Extra: sexp
